mloda/enterprise/compute_frameworks/example/__init__.py
mloda/enterprise/compute_frameworks/example/enterprise_example_compute_framework.py
mloda/enterprise/extenders/example/__init__.py
mloda/enterprise/extenders/example/enterprise_example_extender.py
mloda/enterprise/feature_groups/example/__init__.py
mloda/enterprise/feature_groups/example/enterprise_example_feature_group.py
mloda_enterprise-0.2.6.dist-info/METADATA
mloda_enterprise-0.2.6.dist-info/WHEEL
mloda_enterprise-0.2.6.dist-info/top_level.txt
mloda_enterprise-0.2.6.dist-info/RECORD
