Metadata-Version: 2.4
Name: mloda-enterprise
Version: 0.2.6
Summary: All enterprise plugins for mloda
Author-email: Tom Kaltofen <info@mloda.ai>
License-Expression: LicenseRef-Proprietary
Project-URL: Homepage, https://mloda.ai
Project-URL: Repository, https://github.com/mloda-ai/mloda-registry
Requires-Python: >=3.10
Requires-Dist: mloda>=0.4.3
